cvat_cli/__init__.py
cvat_cli/__main__.py
cvat_cli/version.py
cvat_cli/_internal/__init__.py
cvat_cli/_internal/agent.py
cvat_cli/_internal/command_base.py
cvat_cli/_internal/commands_all.py
cvat_cli/_internal/commands_functions.py
cvat_cli/_internal/commands_projects.py
cvat_cli/_internal/commands_tasks.py
cvat_cli/_internal/common.py
cvat_cli/_internal/parsers.py
cvat_cli/_internal/utils.py
cvat_cli-2.55.0.dist-info/METADATA
cvat_cli-2.55.0.dist-info/WHEEL
cvat_cli-2.55.0.dist-info/entry_points.txt
cvat_cli-2.55.0.dist-info/top_level.txt
cvat_cli-2.55.0.dist-info/RECORD
