Metadata-Version: 2.4
Name: cvat-cli
Version: 2.55.0
Summary: Command-line client for CVAT
Author-email: "CVAT.ai Corporation" <support@cvat.ai>
License-Expression: MIT
Project-URL: homepage, https://github.com/cvat-ai/cvat/
Classifier: Programming Language :: Python :: 3
Classifier: Operating System :: OS Independent
Requires-Python: >=3.10
Requires-Dist: cvat-sdk==2.55.0
Requires-Dist: attrs>=24.2.0
Requires-Dist: Pillow>=10.3.0
